neurofence_sdk/__init__.py
neurofence_sdk/cli.py
neurofence_sdk/client.py
neurofence_sdk/guard.py
neurofence_sdk-1.0.1.dist-info/METADATA
neurofence_sdk-1.0.1.dist-info/WHEEL
neurofence_sdk-1.0.1.dist-info/entry_points.txt
neurofence_sdk-1.0.1.dist-info/top_level.txt
neurofence_sdk-1.0.1.dist-info/RECORD
