Metadata-Version: 2.4
Name: neurofence-sdk
Version: 1.0.1
Summary: NeuroFence SDK - framework-agnostic interception wrapper and API client
Requires-Python: >=3.9
Requires-Dist: requests>=2.28
Dynamic: requires-python
